<actor name="riggle">
  <skeleton filename="Data/Animated Models/Riggle/Skeleton.csf"/>
  <mesh filename="Data/Animated Models/Riggle/Mesh.cmf"/>
  <material animated="true" vertex_type="799">
    <texture type="diffusse" filename="Data/Textures/COLOR_2.dds"/>
    <texture type="normalmap" filename="Data/Textures/NRM_Complet.tga"/>
    <texture type="specular" filename="Data/Textures/Riggle_SPEC.dds"/>
    <texture type="glow" filename="Data/Textures/glow_personatge2.dds"/>
    <property type="glowIntensity" value="2.0" />
    <property type="specularParams" glossiness="200.0" specular_level="10.0" />
  </material>
  <!--
  <animation name="idle" filename="Data/Animated Models/Riggle/idle.CAF"/>
  <animation name="walk" filename="Data/Animated Models/Riggle/walkWeapon.CAF"/>
  <animation name="run" filename="Data/Animated Models/Riggle/runWeapon.CAF"/>
  -->
  <animation name="idle" filename="Data/Animated Models/Riggle/idle.CAF"/>
  <animation name="walk" filename="Data/Animated Models/Riggle/walk_DEF.CAF"/>
  <animation name="run" filename="Data/Animated Models/Riggle/runWeapon.CAF"/>
  
  <animation name="protection" filename="Data/Animated Models/Riggle/protection.CAF"/>
  <animation name="shoot" filename="Data/Animated Models/Riggle/shoot.CAF"/>
  <animation name="impact" filename="Data/Animated Models/Riggle/impact.CAF"/>
  <animation name="aim" filename="Data/Animated Models/Riggle/point.CAF"/>
  
  <animation name="walk back" filename="Data/Animated Models/Riggle/WalkEnrera.CAF"/>
  
  <animation name="CoverAvallDreta" filename="Data/Animated Models/Riggle/CoverAvallDreta.CAF"/>
  <animation name="CoverAvallDretaIdle" filename="Data/Animated Models/Riggle/CoverAvallDretaIdle.CAF"/>
  <animation name="CoverAvallEsquerra" filename="Data/Animated Models/Riggle/CoverAvallEsquerra.CAF"/>
  <animation name="CoverAvallEsquerraIdle" filename="Data/Animated Models/Riggle/CoverAvallEsquerraIdle.CAF"/>
  <animation name="CoverDreta" filename="Data/Animated Models/Riggle/CoverDreta.CAF"/>
  <animation name="CoverDretaIdle" filename="Data/Animated Models/Riggle/CoverDretaIdle.CAF"/>
  <animation name="CoverEsquerra" filename="Data/Animated Models/Riggle/CoverEsquerra.CAF"/>
  <animation name="CoverEsquerraIdle" filename="Data/Animated Models/Riggle/CoverEsquerraIdle.CAF"/>
  <animation name="CoverSortidaDreta" filename="Data/Animated Models/Riggle/CoverSortidaDreta.CAF"/>
  <animation name="CoverSortidaEsquerra" filename="Data/Animated Models/Riggle/CoverSortidaEsquerra.CAF"/>
  <animation name="CoverSortidaAvallDreta" filename="Data/Animated Models/Riggle/CoverSortidaAvallDreta.CAF"/>
  <animation name="CoverSortidaAvallEsquerra" filename="Data/Animated Models/Riggle/CoverSortidaAvallEsquerra.CAF"/>
  
  <animation name="dead" filename="Data/Animated Models/Riggle/dead.CAF"/>

  <animation name="pointDownIdle" filename="Data/Animated Models/Riggle/pointDownIdle.CAF"/>
  <animation name="PointUpIdle" filename="Data/Animated Models/Riggle/PointUpIdle.CAF"/>
  <animation name="PointUpIdleLeft" filename="Data/Animated Models/Riggle/PointUpIdleLeft.CAF"/>
  <animation name="PointUpIdleRight" filename="Data/Animated Models/Riggle/PointUpIdleRight.CAF"/>
  <animation name="pointWalk" filename="Data/Animated Models/Riggle/pointWalk.CAF"/>
  <animation name="pointWalkDown" filename="Data/Animated Models/Riggle/pointWalkDown.CAF"/>
  <animation name="pointWalkUp" filename="Data/Animated Models/Riggle/pointWalkUp.CAF"/>
  <animation name="RiggleDance" filename="Data/Animated Models/Riggle/RiggleDance.CAF"/>
  <animation name="shootDown" filename="Data/Animated Models/Riggle/shootDown.CAF"/>
  <animation name="shootUp" filename="Data/Animated Models/Riggle/shootUp.CAF"/>
  
  
  
  <animation_states default="idle">
    <animation_state name="idle" default_fade_in="0.3" default_fade_out="0.3">
      <cycle name="idle"/>
    </animation_state>
    <!-- -->
    <animation_state name="walk" default_fade_in="0.3" default_fade_out="0.3">
      <cycle name="walk" weight="0.98" />
      <cycle name="run"  weight="0.01" />
      <cycle name="pointWalkUp"   weight="0.01" weight_from_parameter="true"               fade_on_change="0.05"/>
      <cycle name="pointWalkDown" weight="0.01" weight_from_complementary_parameter="true" fade_on_change="0.05"/>
    </animation_state>
    <!-- -->
    <animation_state name="run" default_fade_in="0.3" default_fade_out="0.3">
      <cycle name="walk" weight="0.01" />
      <cycle name="run"  weight="0.98" />
      <cycle name="pointWalkUp"   weight="0.01" weight_from_parameter="true"               fade_on_change="0.05"/>
      <cycle name="pointWalkDown" weight="0.01" weight_from_complementary_parameter="true" fade_on_change="0.05"/>
    </animation_state>
    <!-- -->
    <animation_state name="walk back" default_fade_in="0.3" default_fade_out="0.3">
      <cycle name="walk back"/>
    </animation_state>
    <!-- -->
    <animation_state name="aim" default_fade_in="0.0" default_fade_out="0.3">
      <cycle name="PointUpIdle" weight_from_parameter="true" fade_on_change="0.05"/>
      <cycle name="pointDownIdle" weight_from_complementary_parameter="true" fade_on_change="0.05"/>
    </animation_state>
    <!-- -->
    <animation_state name="walk aim" default_fade_in="0.0" default_fade_out="0.3">
      <cycle name="walk" weight="0.01" />
      <cycle name="run"  weight="0.01" />
      <cycle name="pointWalkUp"   weight="0.98" weight_from_parameter="true"               fade_on_change="0.05"/>
      <cycle name="pointWalkDown" weight="0.98" weight_from_complementary_parameter="true" fade_on_change="0.05"/>
    </animation_state>
    <!-- -->
    <animation_state name="force" default_fade_in="0.0" default_fade_out="0.0">
      <cycle name="protection"/>
    </animation_state>
    <!-- -->
    <animation_state name="die" default_fade_in="0.3" default_fade_out="0.3">
      <on_enter>
        <action name="dead" block="true" fade_in="0.3"/>
      </on_enter>
      <on_exit>
        <action name="dead" stop="true"/>
      </on_exit>
      <cycle name="idle"/>
    </animation_state>
    
    
    <animation_state name="cover down" default_fade_in="0.3" default_fade_out="0.3">
      <cycle name="CoverAvallDretaIdle"/>
    </animation_state>
    <!-- -->
    <animation_state name="cover up" default_fade_in="0.3" default_fade_out="0.3">
      <cycle name="CoverDretaIdle"/>
    </animation_state>
    
    
    <animation_state name="dance" default_fade_in="0.3" default_fade_out="0.3">
      <cycle name="RiggleDance"/>
    </animation_state>
  </animation_states>
  
  <animation_changes>
    <animation_change from="walk aim" to="aim" fade="0.5" />
    <animation_change from="aim" to="walk aim" fade="0.5" />
  </animation_changes>
</actor>
